{"stats":{"minecraft:picked_up":{"minecraft:iron_chestplate":17,"minecraft:wheat":16,"minecraft:redstone_block":11,"minecraft:stone_slab":36,"minecraft:diamond_sword":13,"minecraft:oak_stairs":10,"minecraft:stone_brick_stairs":62,"minecraft:crimson_planks":19,"minecraft:golden_sword":1,"minecraft:polished_blackstone_brick_stairs":1,"minecraft:string":374,"minecraft:iron_leggings":6,"minecraft:oak_sign":32,"minecraft:diamond_leggings":9,"minecraft:gold_nugget":150,"minecraft:bucket":26,"minecraft:spruce_planks":51,"minecraft:cobblestone_slab":112,"minecraft:iron_pickaxe":12,"minecraft:coal_block":76,"minecraft:furnace":6,"minecraft:crimson_sign":69,"minecraft:iron_boots":8,"minecraft:golden_helmet":10,"minecraft:stick":243,"minecraft:polished_blackstone_stairs":10,"minecraft:oak_fence":49,"minecraft:torch":1327,"minecraft:porkchop":107,"minecraft:diorite":377,"minecraft:golden_chestplate":1,"minecraft:rotten_flesh":193,"minecraft:glowstone":43,"minecraft:green_wool":19,"minecraft:cobblestone":6251,"minecraft:birch_log":50,"minecraft:leather_chestplate":2,"minecraft:cooked_beef":124,"minecraft:feather":140,"minecraft:magma_cream":2,"minecraft:water_bucket":8,"minecraft:andesite":985,"minecraft:golden_leggings":2,"minecraft:potato":5,"minecraft:flint":25,"minecraft:lapis_lazuli":518,"minecraft:dirt":741,"minecraft:twisting_vines":15,"minecraft:glass":54,"minecraft:bone":64,"minecraft:bow":4,"minecraft:wheat_seeds":56,"minecraft:diamond_helmet":11,"minecraft:oak_planks":455,"minecraft:cooked_porkchop":21,"minecraft:warped_wart_block":9,"minecraft:oak_pressure_plate":1,"minecraft:sand":120,"minecraft:ink_sac":8,"minecraft:grass_block":113,"minecraft:mossy_cobblestone":46,"minecraft:diamond":268,"minecraft:crossbow":2,"minecraft:granite":108,"minecraft:emerald":105,"minecraft:oak_sapling":9,"minecraft:netherrack":1405,"minecraft:crimson_roots":15,"minecraft:diamond_pickaxe":31,"minecraft:crafting_table":9,"minecraft:chicken":147,"minecraft:ladder":305,"minecraft:stone_brick_wall":5,"minecraft:gold_block":1,"minecraft:shield":8,"minecraft:oak_trapdoor":7,"minecraft:iron_axe":20,"minecraft:compass":3,"minecraft:white_carpet":13,"minecraft:polished_blackstone_wall":1,"minecraft:birch_fence":2,"minecraft:blackstone":63,"minecraft:glass_pane":1,"minecraft:beef":105,"minecraft:poppy":18,"minecraft:observer":21,"minecraft:spruce_slab":8,"minecraft:lectern":1,"minecraft:sugar_cane":398,"minecraft:chest":28,"minecraft:birch_sapling":1,"minecraft:piston":35,"minecraft:spruce_trapdoor":2,"minecraft:phantom_membrane":6,"minecraft:egg":749,"minecraft:lime_wool":8,"minecraft:stone":1274,"minecraft:oak_door":4,"minecraft:spruce_fence":18,"minecraft:polished_blackstone_bricks":3,"minecraft:carrot":6,"minecraft:redstone":750,"minecraft:arrow":262,"minecraft:weeping_vines":8,"minecraft:diamond_chestplate":7,"minecraft:pumpkin_pie":11,"minecraft:diamond_boots":10,"minecraft:saddle":8,"minecraft:totem_of_undying":7,"minecraft:polished_blackstone":14,"minecraft:white_wool":91,"minecraft:clock":1,"minecraft:basalt":236,"minecraft:crimson_stem":3,"minecraft:leather":49,"minecraft:ice":45,"minecraft:crimson_fungus":3,"minecraft:oak_log":136,"minecraft:ancient_debris":2,"minecraft:golden_boots":6,"minecraft:cobblestone_wall":48,"minecraft:gunpowder":121,"minecraft:cobblestone_stairs":192,"minecraft:white_banner":17,"minecraft:podzol":15,"minecraft:stone_bricks":151,"minecraft:kelp":65,"minecraft:warped_stem":46,"minecraft:iron_ingot":303,"minecraft:cobweb":2,"minecraft:cooked_chicken":437,"minecraft:iron_ore":397,"minecraft:iron_sword":9,"minecraft:book":15,"minecraft:oak_slab":465,"minecraft:warped_fungus":16,"minecraft:nether_quartz_ore":16,"minecraft:birch_boat":3,"minecraft:pumpkin":12,"minecraft:stone_brick_slab":35,"minecraft:quartz":93,"minecraft:dandelion":1,"minecraft:gravel":135,"minecraft:spruce_sapling":34,"minecraft:blast_furnace":1,"minecraft:white_bed":7,"minecraft:spruce_log":293,"minecraft:gold_ore":67,"minecraft:crying_obsidian":4,"minecraft:green_carpet":52,"minecraft:spider_eye":172,"minecraft:leather_helmet":1,"minecraft:diamond_shovel":3,"minecraft:coal_ore":25,"minecraft:slime_ball":20,"minecraft:iron_helmet":18,"minecraft:diamond_axe":3,"minecraft:crimson_nylium":125,"minecraft:coal":1436,"minecraft:hopper":7,"minecraft:ender_pearl":17},"minecraft:custom":{"minecraft:animals_bred":7,"minecraft:interact_with_crafting_table":170,"minecraft:open_barrel":87,"minecraft:bell_ring":28,"minecraft:leave_game":11,"minecraft:time_since_death":127664,"minecraft:sprint_one_cm":2683968,"minecraft:damage_blocked_by_shield":2485,"minecraft:drop":231,"minecraft:talked_to_villager":13,"minecraft:deaths":33,"minecraft:jump":7354,"minecraft:interact_with_brewingstand":2,"minecraft:walk_on_water_one_cm":262408,"minecraft:enchant_item":17,"minecraft:interact_with_furnace":141,"minecraft:play_one_minute":1695790,"minecraft:sleep_in_bed":11,"minecraft:damage_dealt":81396,"minecraft:crouch_one_cm":41468,"minecraft:interact_with_smoker":1,"minecraft:horse_one_cm":2480,"minecraft:interact_with_smithing_table":4,"minecraft:interact_with_anvil":20,"minecraft:mob_kills":1539,"minecraft:inspect_hopper":1,"minecraft:climb_one_cm":59940,"minecraft:walk_one_cm":7957979,"minecraft:raid_win":1,"minecraft:sneak_time":30165,"minecraft:walk_under_water_one_cm":68771,"minecraft:boat_one_cm":3513,"minecraft:interact_with_blast_furnace":24,"minecraft:raid_trigger":1,"minecraft:interact_with_stonecutter":4,"minecraft:interact_with_grindstone":6,"minecraft:time_since_rest":117061,"minecraft:damage_taken":18549,"minecraft:swim_one_cm":1198,"minecraft:fly_one_cm":131103,"minecraft:open_chest":828,"minecraft:fall_one_cm":94366},"minecraft:mined":{"minecraft:white_bed":2,"minecraft:cobblestone_stairs":6,"minecraft:spruce_trapdoor":2,"minecraft:granite":263,"minecraft:grass_block":155,"minecraft:stone_brick_wall":5,"minecraft:hopper":3,"minecraft:oak_wall_sign":1,"minecraft:tall_seagrass":4,"minecraft:weeping_vines_plant":1,"minecraft:magma_block":1,"minecraft:glowstone":50,"minecraft:iron_ore":295,"minecraft:fire":9,"minecraft:pumpkin":12,"minecraft:oak_sign":1,"minecraft:oak_stairs":1,"minecraft:green_carpet":37,"minecraft:tripwire":2,"minecraft:spruce_slab":8,"minecraft:blackstone":34,"minecraft:kelp_plant":6,"minecraft:twisting_vines_plant":1,"minecraft:crimson_nylium":153,"minecraft:torch":96,"minecraft:blast_furnace":1,"minecraft:poppy":1,"minecraft:chest":24,"minecraft:nether_quartz_ore":36,"minecraft:glass":3,"minecraft:cobblestone":566,"minecraft:sugar_cane":149,"minecraft:oak_planks":226,"minecraft:wall_torch":124,"minecraft:seagrass":6,"minecraft:warped_nylium":6,"minecraft:nether_wart_block":4,"minecraft:wheat":20,"minecraft:warped_fungus":1,"minecraft:stone_brick_stairs":5,"minecraft:grass":47,"minecraft:oak_log":46,"minecraft:sand":121,"minecraft:dirt":473,"minecraft:crimson_planks":1,"minecraft:netherrack":633,"minecraft:piston":35,"minecraft:oak_leaves":13,"minecraft:nether_gold_ore":22,"minecraft:diamond_ore":147,"minecraft:mossy_cobblestone":46,"minecraft:spruce_fence":3,"minecraft:crimson_roots":10,"minecraft:weeping_vines":2,"minecraft:redstone_wire":1,"minecraft:spruce_leaves":151,"minecraft:kelp":1,"minecraft:large_fern":3,"minecraft:redstone_ore":167,"minecraft:oak_trapdoor":3,"minecraft:furnace":4,"minecraft:andesite":640,"minecraft:bookshelf":5,"minecraft:shroomlight":2,"minecraft:cobblestone_slab":50,"minecraft:stone":7402,"minecraft:podzol":15,"minecraft:oak_slab":5,"minecraft:glass_pane":1,"minecraft:basalt":119,"minecraft:stone_brick_slab":16,"minecraft:observer":17,"minecraft:oak_fence":51,"minecraft:crafting_table":9,"minecraft:honey_block":6,"minecraft:emerald_ore":21,"minecraft:lectern":1,"minecraft:tall_grass":2,"minecraft:lapis_ore":61,"minecraft:diorite":356,"minecraft:warped_wart_block":3,"minecraft:polished_blackstone_stairs":10,"minecraft:ice":45,"minecraft:white_carpet":7,"minecraft:spruce_log":304,"minecraft:coal_ore":840,"minecraft:gravel":78,"minecraft:cobweb":1,"minecraft:crimson_wall_sign":3,"minecraft:polished_blackstone":15,"minecraft:stone_bricks":2,"minecraft:gold_ore":69,"minecraft:birch_fence":2,"minecraft:infested_stone":5,"minecraft:fern":1},"minecraft:dropped":{"minecraft:crimson_nylium":125,"minecraft:warped_fungus":12,"minecraft:cooked_beef":7,"minecraft:oak_log":29,"minecraft:ender_pearl":2,"minecraft:crafting_table":2,"minecraft:weeping_vines":8,"minecraft:flint":14,"minecraft:cobblestone_stairs":19,"minecraft:dirt":37,"minecraft:crimson_roots":15,"minecraft:gold_nugget":73,"minecraft:polished_blackstone_bricks":3,"minecraft:gold_ingot":1,"minecraft:bone":12,"minecraft:gravel":64,"minecraft:polished_blackstone_wall":1,"minecraft:crimson_fungus":3,"minecraft:compass":1,"minecraft:blackstone":42,"minecraft:iron_nugget":18,"minecraft:cooked_chicken":15,"minecraft:twisting_vines":15,"minecraft:rotten_flesh":8,"minecraft:oak_planks":120,"minecraft:chainmail_chestplate":1,"minecraft:gunpowder":3,"minecraft:iron_ore":3,"minecraft:basalt":174,"minecraft:arrow":115,"minecraft:warped_wart_block":9,"minecraft:crying_obsidian":3,"minecraft:quartz":57,"minecraft:netherrack":1193,"minecraft:egg":858,"minecraft:golden_boots":1,"minecraft:water_bucket":1,"minecraft:oak_slab":3,"minecraft:wheat_seeds":3,"minecraft:iron_helmet":1,"minecraft:cobblestone":1249,"minecraft:granite":13,"minecraft:grass_block":22,"minecraft:stick":85,"minecraft:coal_block":38,"minecraft:cobweb":2,"minecraft:diorite":247,"minecraft:torch":60,"minecraft:iron_axe":1,"minecraft:string":6,"minecraft:stone_brick_slab":5,"minecraft:redstone":6,"minecraft:furnace":2,"minecraft:totem_of_undying":1,"minecraft:diamond_sword":3,"minecraft:cobblestone_slab":127,"minecraft:stone":21,"minecraft:diamond_pickaxe":2,"minecraft:iron_chestplate":1,"minecraft:andesite":78,"minecraft:golden_leggings":1,"minecraft:spider_eye":1,"minecraft:nether_quartz_ore":16},"minecraft:crafted":{"minecraft:oak_planks":428,"minecraft:cobblestone_slab":762,"minecraft:oak_sign":30,"minecraft:cooked_chicken":17,"minecraft:birch_boat":1,"minecraft:crimson_sign":21,"minecraft:stone":346,"minecraft:cobblestone_stairs":250,"minecraft:bookshelf":4,"minecraft:spruce_pressure_plate":1,"minecraft:glass":154,"minecraft:hopper":5,"minecraft:stone_brick_slab":1074,"minecraft:diamond_helmet":2,"minecraft:diamond_leggings":2,"minecraft:iron_boots":3,"minecraft:chest":37,"minecraft:stone_bricks":290,"minecraft:golden_boots":2,"minecraft:oak_slab":240,"minecraft:cooked_porkchop":36,"minecraft:crafting_table":3,"minecraft:spruce_planks":1032,"minecraft:baked_potato":7,"minecraft:iron_helmet":2,"minecraft:smithing_table":1,"minecraft:spruce_trapdoor":200,"minecraft:iron_chestplate":3,"minecraft:book":48,"minecraft:paper":192,"minecraft:diamond_pickaxe":6,"minecraft:shield":2,"minecraft:stick":264,"minecraft:stone_slab":6,"minecraft:compass":1,"minecraft:iron_ingot":412,"minecraft:iron_pickaxe":20,"minecraft:iron_block":3,"minecraft:gold_ingot":55,"minecraft:shears":2,"minecraft:green_carpet":18,"minecraft:packed_ice":5,"minecraft:oak_door":3,"minecraft:redstone":189,"minecraft:stone_brick_wall":66,"minecraft:iron_nugget":8,"minecraft:furnace":27,"minecraft:piston":60,"minecraft:bone_meal":1026,"minecraft:spruce_fence":24,"minecraft:white_carpet":15,"minecraft:oak_trapdoor":14,"minecraft:glass_pane":80,"minecraft:flint_and_steel":1,"minecraft:iron_axe":4,"minecraft:spruce_wood":99,"minecraft:spruce_slab":90,"minecraft:cobblestone_wall":508,"minecraft:diamond_boots":2,"minecraft:redstone_block":12,"minecraft:observer":64,"minecraft:cooked_beef":23,"minecraft:coal_block":72,"minecraft:crimson_planks":24,"minecraft:diamond_sword":5,"minecraft:iron_sword":2,"minecraft:bucket":9,"minecraft:air":0,"minecraft:white_wool":19,"minecraft:gold_nugget":29,"minecraft:oak_stairs":8,"minecraft:iron_shovel":1,"minecraft:iron_leggings":3,"minecraft:stonecutter":1,"minecraft:anvil":1,"minecraft:white_bed":3,"minecraft:torch":376,"minecraft:lapis_lazuli":234,"minecraft:diamond_chestplate":3},"minecraft:killed_by":{"minecraft:creeper":2,"minecraft:ravager":4,"minecraft:vindicator":7,"minecraft:cave_spider":9,"minecraft:vex":4,"minecraft:skeleton":2,"minecraft:phantom":1},"minecraft:broken":{"minecraft:iron_boots":1,"minecraft:iron_leggings":1,"minecraft:diamond_pickaxe":1,"minecraft:iron_sword":2,"minecraft:iron_axe":3,"minecraft:iron_pickaxe":19,"minecraft:iron_helmet":1},"minecraft:killed":{"minecraft:cave_spider":40,"minecraft:witch":2,"minecraft:spider":5,"minecraft:skeleton":53,"minecraft:chicken":152,"minecraft:silverfish":2,"minecraft:magma_cube":10,"minecraft:piglin":3,"minecraft:pig":59,"minecraft:zombie_villager":4,"minecraft:creeper":62,"minecraft:pillager":17,"minecraft:zombie":1040,"minecraft:cow":57,"minecraft:vex":1,"minecraft:evoker":1,"minecraft:vindicator":3,"minecraft:slime":3,"minecraft:phantom":11,"minecraft:drowned":1,"minecraft:bat":1,"minecraft:ravager":1,"minecraft:enderman":10},"minecraft:used":{"minecraft:iron_shovel":2,"minecraft:spruce_slab":98,"minecraft:polished_blackstone":14,"minecraft:ladder":12,"minecraft:oak_sign":26,"minecraft:chest":57,"minecraft:shield":23,"minecraft:iron_sword":543,"minecraft:stone":780,"minecraft:rotten_flesh":4,"minecraft:soul_sand":1,"minecraft:carrot":3,"minecraft:obsidian":9,"minecraft:lava_bucket":1,"minecraft:glass":37,"minecraft:packed_ice":5,"minecraft:honey_block":5,"minecraft:grass_block":1,"minecraft:stone_brick_stairs":23,"minecraft:stone_bricks":5,"minecraft:oak_sapling":4,"minecraft:furnace":23,"minecraft:polished_blackstone_stairs":8,"minecraft:diorite":66,"minecraft:oak_planks":105,"minecraft:sugar_cane":62,"minecraft:sand":94,"minecraft:blast_furnace":1,"minecraft:stone_brick_wall":61,"minecraft:shears":1,"minecraft:birch_fence":1,"minecraft:string":25,"minecraft:lectern":1,"minecraft:oak_pressure_plate":1,"minecraft:gravel":19,"minecraft:diamond_sword":1311,"minecraft:smithing_table":1,"minecraft:andesite":283,"minecraft:oak_fence":9,"minecraft:oak_trapdoor":17,"minecraft:redstone":49,"minecraft:cooked_chicken":59,"minecraft:netherrack":798,"minecraft:oak_door":1,"minecraft:torch":619,"minecraft:anvil":1,"minecraft:dirt":357,"minecraft:white_carpet":27,"minecraft:hopper":12,"minecraft:cobblestone_wall":144,"minecraft:granite":14,"minecraft:spruce_fence":22,"minecraft:stone_brick_slab":91,"minecraft:bookshelf":4,"minecraft:iron_axe":717,"minecraft:oak_stairs":8,"minecraft:totem_of_undying":1,"minecraft:crimson_planks":1,"minecraft:basalt":21,"minecraft:golden_carrot":2,"minecraft:cooked_beef":28,"minecraft:observer":77,"minecraft:wheat_seeds":19,"minecraft:water_bucket":114,"minecraft:cobblestone_stairs":46,"minecraft:baked_potato":7,"minecraft:birch_boat":2,"minecraft:stonecutter":1,"minecraft:cobblestone_slab":530,"minecraft:oak_slab":99,"minecraft:crafting_table":10,"minecraft:white_bed":4,"minecraft:cod":5,"minecraft:spruce_log":2,"minecraft:piston":95,"minecraft:diamond_pickaxe":7956,"minecraft:iron_pickaxe":5816,"minecraft:stone_slab":6,"minecraft:spruce_trapdoor":200,"minecraft:chiseled_stone_bricks":1,"minecraft:crimson_sign":23,"minecraft:green_carpet":70,"minecraft:cobblestone":3966,"minecraft:white_banner":1,"minecraft:cooked_porkchop":29,"minecraft:bucket":115,"minecraft:glass_pane":46,"minecraft:pumpkin_pie":11,"minecraft:kelp":65}},"DataVersion":2580}